featuretoolsOnSpark/__init__.py
featuretoolsOnSpark/column_types.py
featuretoolsOnSpark/dfs.py
featuretoolsOnSpark/relationship.py
featuretoolsOnSpark/table.py
featuretoolsOnSpark/tableset.py
featuretoolsOnSpark/version.py
featuretoolsOnSpark-0.1.4.dist-info/LICENSE
featuretoolsOnSpark-0.1.4.dist-info/METADATA
featuretoolsOnSpark-0.1.4.dist-info/WHEEL
featuretoolsOnSpark-0.1.4.dist-info/top_level.txt
featuretoolsOnSpark-0.1.4.dist-info/RECORD
