Metadata-Version: 2.1
Name: featuretoolsOnSpark
Version: 0.1.4
Summary: A simplified version of featuretools for Spark
Home-page: https://github.com/giantcroc/featuretoolsOnSpark
Author: giantcroc
Author-email: 1204449533@qq.com
License: MIT
Keywords: feature engineering data science machine learning
Platform: UNKNOWN
Classifier: Development Status :: 2 - Pre-Alpha
Classifier: Intended Audience :: Developers
Classifier: Programming Language :: Python :: 2.7
Classifier: Programming Language :: Python :: 3
Classifier: Programming Language :: Python :: 3.5
Classifier: Programming Language :: Python :: 3.6
Classifier: Programming Language :: Python :: 3.7
Requires-Python: >=2.7, <4
